pyimaprotect/__init__.py
pyimaprotect/cli.py
pyimaprotect/exceptions.py
pyimaprotect-3.1.6.dist-info/AUTHORS.rst
pyimaprotect-3.1.6.dist-info/LICENSE
pyimaprotect-3.1.6.dist-info/METADATA
pyimaprotect-3.1.6.dist-info/WHEEL
pyimaprotect-3.1.6.dist-info/entry_points.txt
pyimaprotect-3.1.6.dist-info/top_level.txt
pyimaprotect-3.1.6.dist-info/RECORD
