Metadata-Version: 2.1
Name: pyimaprotect
Version: 3.1.6
Summary: Get alarm status and informations from the IMA Protect API.
Home-page: https://github.com/pcourbin/pyimaprotect
Author: Pierre COURBIN
Author-email: pierre.courbin@gmail.com
License: MIT license
Keywords: pyimaprotect
Platform: UNKNOWN
Classifier: Development Status :: 4 - Beta
Classifier: Intended Audience :: Developers
Classifier: License :: OSI Approved :: MIT License
Classifier: Natural Language :: English
Classifier: Programming Language :: Python :: 3
Classifier: Programming Language :: Python :: 3.5
Classifier: Programming Language :: Python :: 3.6
Classifier: Programming Language :: Python :: 3.7
Classifier: Programming Language :: Python :: 3.8
Classifier: Programming Language :: Python :: 3.9
Requires-Python: >=3.5
License-File: LICENSE
License-File: AUTHORS.rst
Requires-Dist: Click (>=7.0)
Requires-Dist: jsonpath-ng (>=1.5.2)
